thalabus/Log.py
thalabus/RemoteSession.py
thalabus/RemoteSessionPool.py
thalabus/__init__.py
thalabus/utils.py
thalabus-1.1.4.dist-info/licenses/LICENSE
thalabus-1.1.4.dist-info/METADATA
thalabus-1.1.4.dist-info/WHEEL
thalabus-1.1.4.dist-info/top_level.txt
thalabus-1.1.4.dist-info/RECORD
