Metadata-Version: 2.4
Name: thalabus
Version: 1.1.4
Summary: An SDK for the thalabus AI chatbot platform
Home-page: https://www.thalabus.com
Author: Luca Strozzi
Author-email: Luca Strozzi <luca.strozzi@t2b.ch>
License: This project is licensed under the MIT License.
Project-URL: Homepage, https://www.thalabus.com
Classifier: Programming Language :: Python :: 3
Classifier: License :: OSI Approved :: MIT License
Classifier: Operating System :: OS Independent
Requires-Python: >=3.9
License-File: LICENSE
Requires-Dist: aiohttp
Requires-Dist: requests
Dynamic: author
Dynamic: classifier
Dynamic: home-page
Dynamic: license-file
Dynamic: requires-python
